CHANGES.txt
COPYRIGHT.txt
LICENSE.txt
README.txt
base.cfg
setup.py
phebe/__init__.py
phebe/connection.py
phebe/gsmaddress.py
phebe/gsmcoding.py
phebe/gsmcoding.txt
phebe/rangelist.py
phebe/rangelist.txt
phebe/response.py
phebe/response.txt
phebe/scriptsupport.py
phebe/shell.py
phebe/sms.py
phebe/tests.py
phebe.egg-info/PKG-INFO
phebe.egg-info/SOURCES.txt
phebe.egg-info/dependency_links.txt
phebe.egg-info/entry_points.txt
phebe.egg-info/requires.txt
phebe.egg-info/top_level.txt
phebe/app/__init__.py
phebe/app/contact.py
phebe/app/message.py
phebe/protocol/__init__.py
phebe/protocol/phonebook.py
phebe/protocol/sms.py
phebe/proxy/__init__.py
phebe/proxy/phonebook.py
phebe/proxy/sms.py