Metadata-Version: 1.0
Name: phebe
Version: 0.2
Summary: Communicate with a mobile phone connected to your computer.
Home-page: http://www.thomas-lotze.de/en/software/phebe/
Author: Thomas Lotze
Author-email: thomas@thomas-lotze.de
License: ZPL 2.1
Keywords: mobile phone at commands phonebook contacts sms
Platform: UNKNOWN
Classifier: Development Status :: 3 - Alpha
Classifier: Environment :: Console
Classifier: License :: OSI Approved :: Zope Public License
Classifier: Programming Language :: Python
Classifier: Topic :: Utilities
